socyti/__init__.py
socyti-0.1.0.dev0.dist-info/METADATA
socyti-0.1.0.dev0.dist-info/WHEEL
socyti-0.1.0.dev0.dist-info/RECORD
