Metadata-Version: 2.3
Name: socyti
Version: 0.1.0.dev0
Summary: A Python package template with src layout
Author: Yasas Senarath
Author-email: 12231659+ysenarath@users.noreply.github.com
Requires-Python: >=3.9
Classifier: Programming Language :: Python :: 3
Classifier: License :: OSI Approved :: MIT License
Classifier: Operating System :: OS Independent
Requires-Dist: importlib-metadata (>=4.0)
Project-URL: Homepage, https://github.com/ysenarath/socyti
Project-URL: Issues, https://github.com/ysenarath/socyti/issues
